featransform/__init__.py
featransform/builder.py
featransform/pipeline.py
featransform/configs/__init__.py
featransform/configs/baseline.py
featransform/core/__init__.py
featransform/core/base.py
featransform/core/constants.py
featransform/core/enums.py
featransform/core/exceptions.py
featransform/core/models.py
featransform/features/__init__.py
featransform/features/anomaly.py
featransform/features/base.py
featransform/features/clustering.py
featransform/features/dimensionality.py
featransform/optimization/__init__.py
featransform/optimization/base.py
featransform/optimization/evaluator.py
featransform/optimization/selector.py
featransform/processing/__init__.py
featransform/processing/encoding.py
featransform/processing/imputation.py
featransform/utils/__init__.py
featransform/utils/data_generator.py
featransform/utils/serializer.py
featransform-1.6.57.dist-info/licenses/LICENSE
featransform-1.6.57.dist-info/METADATA
featransform-1.6.57.dist-info/WHEEL
featransform-1.6.57.dist-info/top_level.txt
featransform-1.6.57.dist-info/RECORD
