Metadata-Version: 2.4
Name: featransform
Version: 1.6.57
Summary: Featransform is an automated feature engineering framework for supervised machine learning
Home-page: https://github.com/TsLu1s/Featransform
Author: Luís Fernando da Silva Santos
Author-email: luisf_ssantos@hotmail.com
License: MIT
Keywords: data science,machine learning,data processing,feature engineering,automated feature engineering,automated machine learning,predictive modeling
Classifier: Intended Audience :: Education
Classifier: Intended Audience :: Developers
Classifier: Intended Audience :: Science/Research
Classifier: Intended Audience :: Customer Service
Classifier: Intended Audience :: Financial and Insurance Industry
Classifier: Intended Audience :: Healthcare Industry
Classifier: Intended Audience :: Telecommunications Industry
Classifier: Topic :: Scientific/Engineering :: Artificial Intelligence
Classifier: Topic :: Scientific/Engineering :: Information Analysis
Classifier: License :: OSI Approved :: MIT License
Classifier: Operating System :: OS Independent
Classifier: Programming Language :: Python :: 3.10
Classifier: Programming Language :: Python :: 3.11
Classifier: Programming Language :: Python :: 3.12
License-File: LICENSE
Requires-Dist: numpy>=1.19.5
Requires-Dist: pandas>=1.2.0
Requires-Dist: scikit-learn>=1.2.2
Requires-Dist: xgboost==2.0.3
Requires-Dist: catboost>=1.2.2
Requires-Dist: pydantic>=2.0.0
Dynamic: author
Dynamic: author-email
Dynamic: classifier
Dynamic: description
Dynamic: description-content-type
Dynamic: home-page
Dynamic: keywords
Dynamic: license
Dynamic: license-file
Dynamic: requires-dist
Dynamic: summary
